haibot_rosgymbullet/__init__.py
haibot_rosgymbullet/envs/__init__.py
haibot_rosgymbullet/envs/haibot_env.py
haibot_rosgymbullet/resources/__init__.py
haibot_rosgymbullet/resources/function_exec_manager.py
haibot_rosgymbullet/resources/plugins/__init__.py
haibot_rosgymbullet/resources/plugins/body_vel_control.py
haibot_rosgymbullet/resources/plugins/control.py
haibot_rosgymbullet/resources/plugins/diff_drive.py
haibot_rosgymbullet/resources/plugins/joint_state_pub.py
haibot_rosgymbullet/resources/plugins/laser_scanner.py
haibot_rosgymbullet/resources/plugins/my_environment.py
haibot_rosgymbullet/resources/plugins/odometry.py
haibot_rosgymbullet/resources/plugins/rgbd_camera.py
haibot_rosgymbullet-0.7.0.dist-info/DESCRIPTION.rst
haibot_rosgymbullet-0.7.0.dist-info/METADATA
haibot_rosgymbullet-0.7.0.dist-info/RECORD
haibot_rosgymbullet-0.7.0.dist-info/WHEEL
haibot_rosgymbullet-0.7.0.dist-info/metadata.json
haibot_rosgymbullet-0.7.0.dist-info/top_level.txt
