Metadata-Version: 2.0
Name: haibot-rosgymbullet
Version: 0.7.0
Summary: DiffBot Ros-Gym-Bullet Environment ( For PYTHON 2.7 )
Home-page: UNKNOWN
License: UNKNOWN
Platform: UNKNOWN
Requires-Dist: gym
Requires-Dist: matplotlib
Requires-Dist: numpy
Requires-Dist: pybullet
